[{"energy":1100.0,"cross_section":0.07992,"asymmetry_parameter":2},{"energy":1150.0,"cross_section":0.07634,"asymmetry_parameter":2},{"energy":1200.0,"cross_section":0.07193,"asymmetry_parameter":2},{"energy":1250.0,"cross_section":0.06787,"asymmetry_parameter":2},{"energy":1253.6,"cross_section":0.06757,"asymmetry_parameter":2},{"energy":1300.0,"cross_section":0.0641,"asymmetry_parameter":2},{"energy":1350.0,"cross_section":0.06057,"asymmetry_parameter":2},{"energy":1400.0,"cross_section":0.05737,"asymmetry_parameter":2},{"energy":1450.0,"cross_section":0.05438,"asymmetry_parameter":2},{"energy":1486.6,"cross_section":0.05236,"asymmetry_parameter":2},{"energy":1500.0,"cross_section":0.05165,"asymmetry_parameter":2}]