[{"energy":90.0,"cross_section":0.6935,"asymmetry_parameter":1.245},{"energy":95.0,"cross_section":0.629,"asymmetry_parameter":1.519},{"energy":100.0,"cross_section":0.537,"asymmetry_parameter":1.21},{"energy":105.0,"cross_section":0.4645,"asymmetry_parameter":0.867},{"energy":110.0,"cross_section":0.4096,"asymmetry_parameter":0.5654},{"energy":115.0,"cross_section":0.3681,"asymmetry_parameter":0.3131},{"energy":120.0,"cross_section":0.3369,"asymmetry_parameter":0.1104},{"energy":125.0,"cross_section":0.314,"asymmetry_parameter":-0.04251},{"energy":130.0,"cross_section":0.2975,"asymmetry_parameter":-0.147},{"energy":132.3,"cross_section":0.2916,"asymmetry_parameter":-0.1799},{"energy":135.0,"cross_section":0.2858,"asymmetry_parameter":-0.2076},{"energy":140.0,"cross_section":0.2776,"asymmetry_parameter":-0.2316},{"energy":145.0,"cross_section":0.2719,"asymmetry_parameter":-0.2275},{"energy":150.0,"cross_section":0.2679,"asymmetry_parameter":-0.2034},{"energy":151.4,"cross_section":0.267,"asymmetry_parameter":-0.194},{"energy":155.0,"cross_section":0.2649,"asymmetry_parameter":-0.1659},{"energy":160.0,"cross_section":0.2627,"asymmetry_parameter":-0.1199},{"energy":165.0,"cross_section":0.2608,"asymmetry_parameter":-0.06881},{"energy":170.0,"cross_section":0.2591,"asymmetry_parameter":-0.01489},{"energy":175.0,"cross_section":0.2576,"asymmetry_parameter":0.04036},{"energy":180.0,"cross_section":0.2561,"asymmetry_parameter":0.09598},{"energy":185.0,"cross_section":0.2547,"asymmetry_parameter":0.1513},{"energy":190.0,"cross_section":0.2532,"asymmetry_parameter":0.2057},{"energy":195.0,"cross_section":0.2517,"asymmetry_parameter":0.2589},{"energy":200.0,"cross_section":0.2501,"asymmetry_parameter":0.3104},{"energy":205.0,"cross_section":0.2485,"asymmetry_parameter":0.3601},{"energy":210.0,"cross_section":0.2467,"asymmetry_parameter":0.4077},{"energy":215.0,"cross_section":0.2449,"asymmetry_parameter":0.4531},{"energy":220.0,"cross_section":0.243,"asymmetry_parameter":0.4962},{"energy":225.0,"cross_section":0.241,"asymmetry_parameter":0.5371},{"energy":230.0,"cross_section":0.239,"asymmetry_parameter":0.5758},{"energy":235.0,"cross_section":0.2369,"asymmetry_parameter":0.6124},{"energy":240.0,"cross_section":0.2347,"asymmetry_parameter":0.647},{"energy":245.0,"cross_section":0.2325,"asymmetry_parameter":0.6799},{"energy":250.0,"cross_section":0.2303,"asymmetry_parameter":0.7111},{"energy":255.0,"cross_section":0.228,"asymmetry_parameter":0.7407},{"energy":260.0,"cross_section":0.2257,"asymmetry_parameter":0.769},{"energy":265.0,"cross_section":0.2233,"asymmetry_parameter":0.7961},{"energy":270.0,"cross_section":0.221,"asymmetry_parameter":0.822},{"energy":275.0,"cross_section":0.2186,"asymmetry_parameter":0.8468},{"energy":280.0,"cross_section":0.2162,"asymmetry_parameter":0.8706},{"energy":285.0,"cross_section":0.2138,"asymmetry_parameter":0.8935},{"energy":290.0,"cross_section":0.2114,"asymmetry_parameter":0.9154},{"energy":295.0,"cross_section":0.209,"asymmetry_parameter":0.9366},{"energy":300.0,"cross_section":0.2066,"asymmetry_parameter":0.9569},{"energy":305.0,"cross_section":0.2042,"asymmetry_parameter":0.9764},{"energy":310.0,"cross_section":0.2018,"asymmetry_parameter":0.9951},{"energy":315.0,"cross_section":0.1994,"asymmetry_parameter":1.013},{"energy":320.0,"cross_section":0.197,"asymmetry_parameter":1.03},{"energy":325.0,"cross_section":0.1947,"asymmetry_parameter":1.047},{"energy":330.0,"cross_section":0.1923,"asymmetry_parameter":1.063},{"energy":335.0,"cross_section":0.19,"asymmetry_parameter":1.078},{"energy":340.0,"cross_section":0.1877,"asymmetry_parameter":1.093},{"energy":345.0,"cross_section":0.1854,"asymmetry_parameter":1.107},{"energy":350.0,"cross_section":0.1832,"asymmetry_parameter":1.121},{"energy":355.0,"cross_section":0.181,"asymmetry_parameter":1.134},{"energy":360.0,"cross_section":0.1788,"asymmetry_parameter":1.146},{"energy":365.0,"cross_section":0.1766,"asymmetry_parameter":1.159},{"energy":370.0,"cross_section":0.1745,"asymmetry_parameter":1.17},{"energy":375.0,"cross_section":0.1724,"asymmetry_parameter":1.182},{"energy":380.0,"cross_section":0.1703,"asymmetry_parameter":1.193},{"energy":385.0,"cross_section":0.1683,"asymmetry_parameter":1.204},{"energy":400.0,"cross_section":0.1623,"asymmetry_parameter":1.234},{"energy":420.0,"cross_section":0.1546,"asymmetry_parameter":1.271},{"energy":440.0,"cross_section":0.1474,"asymmetry_parameter":1.304},{"energy":460.0,"cross_section":0.1406,"asymmetry_parameter":1.333},{"energy":480.0,"cross_section":0.1342,"asymmetry_parameter":1.36},{"energy":500.0,"cross_section":0.1283,"asymmetry_parameter":1.384},{"energy":520.0,"cross_section":0.1227,"asymmetry_parameter":1.405},{"energy":540.0,"cross_section":0.1174,"asymmetry_parameter":1.425},{"energy":560.0,"cross_section":0.1124,"asymmetry_parameter":1.443},{"energy":580.0,"cross_section":0.1077,"asymmetry_parameter":1.46},{"energy":600.0,"cross_section":0.1033,"asymmetry_parameter":1.475},{"energy":620.0,"cross_section":0.09913,"asymmetry_parameter":1.49},{"energy":640.0,"cross_section":0.09522,"asymmetry_parameter":1.503},{"energy":660.0,"cross_section":0.09153,"asymmetry_parameter":1.515},{"energy":680.0,"cross_section":0.08805,"asymmetry_parameter":1.526},{"energy":700.0,"cross_section":0.08476,"asymmetry_parameter":1.537},{"energy":720.0,"cross_section":0.08165,"asymmetry_parameter":1.546},{"energy":740.0,"cross_section":0.07869,"asymmetry_parameter":1.556},{"energy":760.0,"cross_section":0.07589,"asymmetry_parameter":1.564},{"energy":780.0,"cross_section":0.07324,"asymmetry_parameter":1.572},{"energy":800.0,"cross_section":0.07073,"asymmetry_parameter":1.58},{"energy":850.0,"cross_section":0.06499,"asymmetry_parameter":1.597},{"energy":900.0,"cross_section":0.05991,"asymmetry_parameter":1.611},{"energy":950.0,"cross_section":0.0554,"asymmetry_parameter":1.624},{"energy":1000.0,"cross_section":0.05139,"asymmetry_parameter":1.635},{"energy":1041.0,"cross_section":0.04842,"asymmetry_parameter":1.643},{"energy":1050.0,"cross_section":0.0478,"asymmetry_parameter":1.645},{"energy":1100.0,"cross_section":0.04457,"asymmetry_parameter":1.653},{"energy":1150.0,"cross_section":0.04166,"asymmetry_parameter":1.661},{"energy":1200.0,"cross_section":0.03902,"asymmetry_parameter":1.667},{"energy":1250.0,"cross_section":0.03663,"asymmetry_parameter":1.673},{"energy":1253.6,"cross_section":0.03647,"asymmetry_parameter":1.673},{"energy":1300.0,"cross_section":0.03446,"asymmetry_parameter":1.678},{"energy":1350.0,"cross_section":0.03246,"asymmetry_parameter":1.682},{"energy":1400.0,"cross_section":0.03064,"asymmetry_parameter":1.686},{"energy":1450.0,"cross_section":0.02897,"asymmetry_parameter":1.69},{"energy":1486.6,"cross_section":0.02783,"asymmetry_parameter":1.692},{"energy":1500.0,"cross_section":0.02743,"asymmetry_parameter":1.693}]