[{"energy":150.0,"cross_section":683.0,"asymmetry_parameter":0.6564},{"energy":155.0,"cross_section":0.3716,"asymmetry_parameter":0.3562},{"energy":160.0,"cross_section":0.3939,"asymmetry_parameter":0.486},{"energy":165.0,"cross_section":0.3883,"asymmetry_parameter":0.6994},{"energy":170.0,"cross_section":0.3831,"asymmetry_parameter":0.9905},{"energy":175.0,"cross_section":0.3898,"asymmetry_parameter":1.31},{"energy":180.0,"cross_section":0.4136,"asymmetry_parameter":1.577},{"energy":185.0,"cross_section":0.4582,"asymmetry_parameter":1.735},{"energy":190.0,"cross_section":0.522,"asymmetry_parameter":1.764},{"energy":195.0,"cross_section":0.6051,"asymmetry_parameter":1.698},{"energy":200.0,"cross_section":0.7089,"asymmetry_parameter":1.577},{"energy":205.0,"cross_section":0.8347,"asymmetry_parameter":1.429},{"energy":210.0,"cross_section":0.9832,"asymmetry_parameter":1.274},{"energy":215.0,"cross_section":1.154,"asymmetry_parameter":1.124},{"energy":220.0,"cross_section":1.343,"asymmetry_parameter":0.9858},{"energy":225.0,"cross_section":1.548,"asymmetry_parameter":0.8629},{"energy":230.0,"cross_section":1.764,"asymmetry_parameter":0.756},{"energy":235.0,"cross_section":1.985,"asymmetry_parameter":0.6648},{"energy":240.0,"cross_section":2.21,"asymmetry_parameter":0.5878},{"energy":245.0,"cross_section":2.434,"asymmetry_parameter":0.5235},{"energy":250.0,"cross_section":2.656,"asymmetry_parameter":0.4701},{"energy":255.0,"cross_section":2.874,"asymmetry_parameter":0.426},{"energy":260.0,"cross_section":3.087,"asymmetry_parameter":0.3898},{"energy":265.0,"cross_section":3.294,"asymmetry_parameter":0.3604},{"energy":270.0,"cross_section":3.491,"asymmetry_parameter":0.3365},{"energy":275.0,"cross_section":3.679,"asymmetry_parameter":0.3174},{"energy":280.0,"cross_section":3.855,"asymmetry_parameter":0.3023},{"energy":285.0,"cross_section":4.018,"asymmetry_parameter":0.2906},{"energy":290.0,"cross_section":4.167,"asymmetry_parameter":0.2819},{"energy":295.0,"cross_section":4.302,"asymmetry_parameter":0.2756},{"energy":300.0,"cross_section":4.423,"asymmetry_parameter":0.2715},{"energy":305.0,"cross_section":4.53,"asymmetry_parameter":0.2692},{"energy":310.0,"cross_section":4.625,"asymmetry_parameter":0.2685},{"energy":315.0,"cross_section":4.708,"asymmetry_parameter":0.2691},{"energy":320.0,"cross_section":4.78,"asymmetry_parameter":0.271},{"energy":325.0,"cross_section":4.841,"asymmetry_parameter":0.2738},{"energy":330.0,"cross_section":4.894,"asymmetry_parameter":0.2776},{"energy":335.0,"cross_section":4.937,"asymmetry_parameter":0.2821},{"energy":340.0,"cross_section":4.972,"asymmetry_parameter":0.2872},{"energy":345.0,"cross_section":5.0,"asymmetry_parameter":0.2928},{"energy":350.0,"cross_section":5.019,"asymmetry_parameter":0.2989},{"energy":355.0,"cross_section":5.032,"asymmetry_parameter":0.3054},{"energy":360.0,"cross_section":5.038,"asymmetry_parameter":0.3122},{"energy":365.0,"cross_section":5.037,"asymmetry_parameter":0.3193},{"energy":370.0,"cross_section":5.03,"asymmetry_parameter":0.3266},{"energy":375.0,"cross_section":5.018,"asymmetry_parameter":0.334},{"energy":380.0,"cross_section":5.0,"asymmetry_parameter":0.3416},{"energy":385.0,"cross_section":4.978,"asymmetry_parameter":0.3494},{"energy":390.0,"cross_section":4.952,"asymmetry_parameter":0.3572},{"energy":395.0,"cross_section":4.922,"asymmetry_parameter":0.3651},{"energy":400.0,"cross_section":4.889,"asymmetry_parameter":0.373},{"energy":405.0,"cross_section":4.853,"asymmetry_parameter":0.381},{"energy":410.0,"cross_section":4.815,"asymmetry_parameter":0.389},{"energy":415.0,"cross_section":4.775,"asymmetry_parameter":0.3971},{"energy":420.0,"cross_section":4.733,"asymmetry_parameter":0.4051},{"energy":425.0,"cross_section":4.689,"asymmetry_parameter":0.4131},{"energy":430.0,"cross_section":4.644,"asymmetry_parameter":0.4211},{"energy":435.0,"cross_section":4.597,"asymmetry_parameter":0.4291},{"energy":440.0,"cross_section":4.55,"asymmetry_parameter":0.4371},{"energy":445.0,"cross_section":4.501,"asymmetry_parameter":0.4449},{"energy":460.0,"cross_section":4.349,"asymmetry_parameter":0.4683},{"energy":480.0,"cross_section":4.139,"asymmetry_parameter":0.4984},{"energy":500.0,"cross_section":3.925,"asymmetry_parameter":0.5272},{"energy":520.0,"cross_section":3.713,"asymmetry_parameter":0.5547},{"energy":540.0,"cross_section":3.507,"asymmetry_parameter":0.5809},{"energy":560.0,"cross_section":3.308,"asymmetry_parameter":0.6058},{"energy":580.0,"cross_section":3.118,"asymmetry_parameter":0.6295},{"energy":600.0,"cross_section":2.937,"asymmetry_parameter":0.652},{"energy":620.0,"cross_section":2.765,"asymmetry_parameter":0.6733},{"energy":640.0,"cross_section":2.602,"asymmetry_parameter":0.6935},{"energy":660.0,"cross_section":2.449,"asymmetry_parameter":0.7125},{"energy":680.0,"cross_section":2.305,"asymmetry_parameter":0.7306},{"energy":700.0,"cross_section":2.17,"asymmetry_parameter":0.7478},{"energy":720.0,"cross_section":2.044,"asymmetry_parameter":0.764},{"energy":740.0,"cross_section":1.925,"asymmetry_parameter":0.7794},{"energy":760.0,"cross_section":1.814,"asymmetry_parameter":0.794},{"energy":780.0,"cross_section":1.711,"asymmetry_parameter":0.8079},{"energy":800.0,"cross_section":1.614,"asymmetry_parameter":0.821},{"energy":850.0,"cross_section":1.398,"asymmetry_parameter":0.8509},{"energy":900.0,"cross_section":1.216,"asymmetry_parameter":0.8772},{"energy":950.0,"cross_section":1.061,"asymmetry_parameter":0.9002},{"energy":1000.0,"cross_section":0.929,"asymmetry_parameter":0.9204},{"energy":1041.0,"cross_section":0.8357,"asymmetry_parameter":0.9352},{"energy":1050.0,"cross_section":0.8167,"asymmetry_parameter":0.9382},{"energy":1100.0,"cross_section":0.7205,"asymmetry_parameter":0.9538},{"energy":1150.0,"cross_section":0.6379,"asymmetry_parameter":0.9675},{"energy":1200.0,"cross_section":0.5666,"asymmetry_parameter":0.9795},{"energy":1250.0,"cross_section":0.5049,"asymmetry_parameter":0.9899},{"energy":1253.6,"cross_section":0.5007,"asymmetry_parameter":0.9906},{"energy":1300.0,"cross_section":0.4512,"asymmetry_parameter":0.9991},{"energy":1350.0,"cross_section":0.4044,"asymmetry_parameter":1.007},{"energy":1400.0,"cross_section":0.3635,"asymmetry_parameter":1.014},{"energy":1450.0,"cross_section":0.3275,"asymmetry_parameter":1.02},{"energy":1486.6,"cross_section":0.304,"asymmetry_parameter":1.024},{"energy":1500.0,"cross_section":0.2959,"asymmetry_parameter":1.025}]