[{"energy":50.0,"cross_section":3.393,"asymmetry_parameter":1.912},{"energy":55.0,"cross_section":2.494,"asymmetry_parameter":1.986},{"energy":60.0,"cross_section":1.754,"asymmetry_parameter":1.897},{"energy":65.0,"cross_section":1.243,"asymmetry_parameter":1.725},{"energy":70.0,"cross_section":0.9079,"asymmetry_parameter":1.496},{"energy":75.0,"cross_section":0.6896,"asymmetry_parameter":1.229},{"energy":80.0,"cross_section":0.5452,"asymmetry_parameter":0.9482},{"energy":85.0,"cross_section":0.4476,"asymmetry_parameter":0.6744},{"energy":90.0,"cross_section":0.3805,"asymmetry_parameter":0.4264},{"energy":95.0,"cross_section":0.3337,"asymmetry_parameter":0.2185},{"energy":100.0,"cross_section":0.3008,"asymmetry_parameter":0.05895},{"energy":105.0,"cross_section":0.2775,"asymmetry_parameter":-0.0507},{"energy":110.0,"cross_section":0.2608,"asymmetry_parameter":-0.1145},{"energy":115.0,"cross_section":0.2488,"asymmetry_parameter":-0.1401},{"energy":120.0,"cross_section":0.2399,"asymmetry_parameter":-0.1363},{"energy":125.0,"cross_section":0.2331,"asymmetry_parameter":-0.1114},{"energy":130.0,"cross_section":0.2278,"asymmetry_parameter":-0.07232},{"energy":132.3,"cross_section":0.2256,"asymmetry_parameter":-0.05108},{"energy":135.0,"cross_section":0.2234,"asymmetry_parameter":-0.02429},{"energy":140.0,"cross_section":0.2196,"asymmetry_parameter":0.02892},{"energy":145.0,"cross_section":0.2163,"asymmetry_parameter":0.08474},{"energy":150.0,"cross_section":0.2132,"asymmetry_parameter":0.1415},{"energy":151.4,"cross_section":0.2124,"asymmetry_parameter":0.1574},{"energy":155.0,"cross_section":0.2103,"asymmetry_parameter":0.198},{"energy":160.0,"cross_section":0.2075,"asymmetry_parameter":0.2536},{"energy":165.0,"cross_section":0.2048,"asymmetry_parameter":0.3077},{"energy":170.0,"cross_section":0.2022,"asymmetry_parameter":0.36},{"energy":175.0,"cross_section":0.1995,"asymmetry_parameter":0.4105},{"energy":180.0,"cross_section":0.1969,"asymmetry_parameter":0.4587},{"energy":185.0,"cross_section":0.1943,"asymmetry_parameter":0.5048},{"energy":190.0,"cross_section":0.1916,"asymmetry_parameter":0.5487},{"energy":195.0,"cross_section":0.189,"asymmetry_parameter":0.5903},{"energy":200.0,"cross_section":0.1864,"asymmetry_parameter":0.6298},{"energy":205.0,"cross_section":0.1838,"asymmetry_parameter":0.6672},{"energy":210.0,"cross_section":0.1811,"asymmetry_parameter":0.7025},{"energy":215.0,"cross_section":0.1785,"asymmetry_parameter":0.736},{"energy":220.0,"cross_section":0.1759,"asymmetry_parameter":0.7677},{"energy":225.0,"cross_section":0.1734,"asymmetry_parameter":0.7978},{"energy":230.0,"cross_section":0.1708,"asymmetry_parameter":0.8263},{"energy":235.0,"cross_section":0.1683,"asymmetry_parameter":0.8534},{"energy":240.0,"cross_section":0.1658,"asymmetry_parameter":0.8793},{"energy":245.0,"cross_section":0.1633,"asymmetry_parameter":0.904},{"energy":250.0,"cross_section":0.1609,"asymmetry_parameter":0.9275},{"energy":255.0,"cross_section":0.1584,"asymmetry_parameter":0.9501},{"energy":260.0,"cross_section":0.1561,"asymmetry_parameter":0.9717},{"energy":265.0,"cross_section":0.1537,"asymmetry_parameter":0.9924},{"energy":270.0,"cross_section":0.1514,"asymmetry_parameter":1.012},{"energy":275.0,"cross_section":0.1491,"asymmetry_parameter":1.031},{"energy":280.0,"cross_section":0.1469,"asymmetry_parameter":1.05},{"energy":285.0,"cross_section":0.1447,"asymmetry_parameter":1.067},{"energy":290.0,"cross_section":0.1425,"asymmetry_parameter":1.084},{"energy":295.0,"cross_section":0.1404,"asymmetry_parameter":1.1},{"energy":300.0,"cross_section":0.1382,"asymmetry_parameter":1.116},{"energy":305.0,"cross_section":0.1362,"asymmetry_parameter":1.131},{"energy":310.0,"cross_section":0.1341,"asymmetry_parameter":1.145},{"energy":315.0,"cross_section":0.1322,"asymmetry_parameter":1.159},{"energy":320.0,"cross_section":0.1302,"asymmetry_parameter":1.173},{"energy":325.0,"cross_section":0.1283,"asymmetry_parameter":1.186},{"energy":330.0,"cross_section":0.1264,"asymmetry_parameter":1.198},{"energy":335.0,"cross_section":0.1246,"asymmetry_parameter":1.21},{"energy":340.0,"cross_section":0.1228,"asymmetry_parameter":1.221},{"energy":345.0,"cross_section":0.121,"asymmetry_parameter":1.233},{"energy":360.0,"cross_section":0.1159,"asymmetry_parameter":1.264},{"energy":380.0,"cross_section":0.1095,"asymmetry_parameter":1.301},{"energy":400.0,"cross_section":0.1036,"asymmetry_parameter":1.334},{"energy":420.0,"cross_section":0.0982,"asymmetry_parameter":1.364},{"energy":440.0,"cross_section":0.09316,"asymmetry_parameter":1.391},{"energy":460.0,"cross_section":0.08848,"asymmetry_parameter":1.414},{"energy":480.0,"cross_section":0.08415,"asymmetry_parameter":1.436},{"energy":500.0,"cross_section":0.08013,"asymmetry_parameter":1.455},{"energy":520.0,"cross_section":0.07639,"asymmetry_parameter":1.473},{"energy":540.0,"cross_section":0.07291,"asymmetry_parameter":1.489},{"energy":560.0,"cross_section":0.06966,"asymmetry_parameter":1.504},{"energy":580.0,"cross_section":0.06662,"asymmetry_parameter":1.518},{"energy":600.0,"cross_section":0.06378,"asymmetry_parameter":1.531},{"energy":620.0,"cross_section":0.06112,"asymmetry_parameter":1.542},{"energy":640.0,"cross_section":0.05862,"asymmetry_parameter":1.553},{"energy":660.0,"cross_section":0.05628,"asymmetry_parameter":1.563},{"energy":680.0,"cross_section":0.05408,"asymmetry_parameter":1.572},{"energy":700.0,"cross_section":0.052,"asymmetry_parameter":1.581},{"energy":720.0,"cross_section":0.05004,"asymmetry_parameter":1.589},{"energy":740.0,"cross_section":0.0482,"asymmetry_parameter":1.596},{"energy":760.0,"cross_section":0.04645,"asymmetry_parameter":1.603},{"energy":780.0,"cross_section":0.0448,"asymmetry_parameter":1.61},{"energy":800.0,"cross_section":0.04324,"asymmetry_parameter":1.616},{"energy":850.0,"cross_section":0.03967,"asymmetry_parameter":1.63},{"energy":900.0,"cross_section":0.03653,"asymmetry_parameter":1.641},{"energy":950.0,"cross_section":0.03375,"asymmetry_parameter":1.651},{"energy":1000.0,"cross_section":0.03128,"asymmetry_parameter":1.66},{"energy":1041.0,"cross_section":0.02945,"asymmetry_parameter":1.666},{"energy":1050.0,"cross_section":0.02907,"asymmetry_parameter":1.667},{"energy":1100.0,"cross_section":0.02709,"asymmetry_parameter":1.674},{"energy":1150.0,"cross_section":0.0253,"asymmetry_parameter":1.679},{"energy":1200.0,"cross_section":0.02368,"asymmetry_parameter":1.684},{"energy":1250.0,"cross_section":0.02221,"asymmetry_parameter":1.688},{"energy":1253.6,"cross_section":0.02211,"asymmetry_parameter":1.689},{"energy":1300.0,"cross_section":0.02087,"asymmetry_parameter":1.692},{"energy":1350.0,"cross_section":0.01965,"asymmetry_parameter":1.695},{"energy":1400.0,"cross_section":0.01853,"asymmetry_parameter":1.698},{"energy":1450.0,"cross_section":0.0175,"asymmetry_parameter":1.7},{"energy":1486.6,"cross_section":0.0168,"asymmetry_parameter":1.701},{"energy":1500.0,"cross_section":0.01656,"asymmetry_parameter":1.702}]