[{"energy":200.0,"cross_section":0.2356,"asymmetry_parameter":2},{"energy":220.0,"cross_section":0.2421,"asymmetry_parameter":2},{"energy":240.0,"cross_section":0.2219,"asymmetry_parameter":2},{"energy":260.0,"cross_section":0.2032,"asymmetry_parameter":2},{"energy":280.0,"cross_section":0.1885,"asymmetry_parameter":2},{"energy":300.0,"cross_section":0.1751,"asymmetry_parameter":2},{"energy":320.0,"cross_section":0.1622,"asymmetry_parameter":2},{"energy":340.0,"cross_section":0.1503,"asymmetry_parameter":2},{"energy":360.0,"cross_section":0.1398,"asymmetry_parameter":2},{"energy":380.0,"cross_section":0.1304,"asymmetry_parameter":2},{"energy":400.0,"cross_section":0.1219,"asymmetry_parameter":2},{"energy":420.0,"cross_section":0.1141,"asymmetry_parameter":2},{"energy":440.0,"cross_section":0.107,"asymmetry_parameter":2},{"energy":460.0,"cross_section":0.1005,"asymmetry_parameter":2},{"energy":480.0,"cross_section":0.09455,"asymmetry_parameter":2},{"energy":500.0,"cross_section":0.08914,"asymmetry_parameter":2},{"energy":520.0,"cross_section":0.0842,"asymmetry_parameter":2},{"energy":540.0,"cross_section":0.07964,"asymmetry_parameter":2},{"energy":560.0,"cross_section":0.07543,"asymmetry_parameter":2},{"energy":580.0,"cross_section":0.07153,"asymmetry_parameter":2},{"energy":600.0,"cross_section":0.06792,"asymmetry_parameter":2},{"energy":620.0,"cross_section":0.06458,"asymmetry_parameter":2},{"energy":640.0,"cross_section":0.06148,"asymmetry_parameter":2},{"energy":660.0,"cross_section":0.0586,"asymmetry_parameter":2},{"energy":680.0,"cross_section":0.05592,"asymmetry_parameter":2},{"energy":700.0,"cross_section":0.05342,"asymmetry_parameter":2},{"energy":720.0,"cross_section":0.05108,"asymmetry_parameter":2},{"energy":740.0,"cross_section":0.04888,"asymmetry_parameter":2},{"energy":760.0,"cross_section":0.04683,"asymmetry_parameter":2},{"energy":780.0,"cross_section":0.0449,"asymmetry_parameter":2},{"energy":800.0,"cross_section":0.04309,"asymmetry_parameter":2},{"energy":850.0,"cross_section":0.03901,"asymmetry_parameter":2},{"energy":900.0,"cross_section":0.03549,"asymmetry_parameter":2},{"energy":950.0,"cross_section":0.03241,"asymmetry_parameter":2},{"energy":1000.0,"cross_section":0.02972,"asymmetry_parameter":2},{"energy":1041.0,"cross_section":0.02776,"asymmetry_parameter":2},{"energy":1050.0,"cross_section":0.02736,"asymmetry_parameter":2},{"energy":1100.0,"cross_section":0.02526,"asymmetry_parameter":2},{"energy":1150.0,"cross_section":0.0234,"asymmetry_parameter":2},{"energy":1200.0,"cross_section":0.02173,"asymmetry_parameter":2},{"energy":1250.0,"cross_section":0.02024,"asymmetry_parameter":2},{"energy":1253.6,"cross_section":0.02014,"asymmetry_parameter":2},{"energy":1300.0,"cross_section":0.01889,"asymmetry_parameter":2},{"energy":1350.0,"cross_section":0.01768,"asymmetry_parameter":2},{"energy":1400.0,"cross_section":0.01657,"asymmetry_parameter":2},{"energy":1450.0,"cross_section":0.01557,"asymmetry_parameter":2},{"energy":1486.6,"cross_section":0.0149,"asymmetry_parameter":2},{"energy":1500.0,"cross_section":0.01466,"asymmetry_parameter":2}]