[{"energy":340.0,"cross_section":0.3839,"asymmetry_parameter":-0.7011},{"energy":360.0,"cross_section":0.3755,"asymmetry_parameter":-0.2854},{"energy":380.0,"cross_section":0.3739,"asymmetry_parameter":0.05564},{"energy":400.0,"cross_section":0.3703,"asymmetry_parameter":0.3119},{"energy":420.0,"cross_section":0.365,"asymmetry_parameter":0.5008},{"energy":440.0,"cross_section":0.3592,"asymmetry_parameter":0.6509},{"energy":460.0,"cross_section":0.3524,"asymmetry_parameter":0.7729},{"energy":480.0,"cross_section":0.3448,"asymmetry_parameter":0.872},{"energy":500.0,"cross_section":0.337,"asymmetry_parameter":0.9545},{"energy":520.0,"cross_section":0.3289,"asymmetry_parameter":1.025},{"energy":540.0,"cross_section":0.3205,"asymmetry_parameter":1.086},{"energy":560.0,"cross_section":0.312,"asymmetry_parameter":1.138},{"energy":580.0,"cross_section":0.3035,"asymmetry_parameter":1.184},{"energy":600.0,"cross_section":0.2952,"asymmetry_parameter":1.224},{"energy":620.0,"cross_section":0.287,"asymmetry_parameter":1.26},{"energy":640.0,"cross_section":0.2788,"asymmetry_parameter":1.292},{"energy":660.0,"cross_section":0.2709,"asymmetry_parameter":1.321},{"energy":680.0,"cross_section":0.2631,"asymmetry_parameter":1.347},{"energy":700.0,"cross_section":0.2556,"asymmetry_parameter":1.371},{"energy":720.0,"cross_section":0.2483,"asymmetry_parameter":1.392},{"energy":740.0,"cross_section":0.2411,"asymmetry_parameter":1.411},{"energy":760.0,"cross_section":0.2343,"asymmetry_parameter":1.429},{"energy":780.0,"cross_section":0.2276,"asymmetry_parameter":1.446},{"energy":800.0,"cross_section":0.2211,"asymmetry_parameter":1.461},{"energy":850.0,"cross_section":0.206,"asymmetry_parameter":1.494},{"energy":900.0,"cross_section":0.1921,"asymmetry_parameter":1.521},{"energy":950.0,"cross_section":0.1794,"asymmetry_parameter":1.544},{"energy":1000.0,"cross_section":0.1678,"asymmetry_parameter":1.563},{"energy":1041.0,"cross_section":0.159,"asymmetry_parameter":1.577},{"energy":1050.0,"cross_section":0.1571,"asymmetry_parameter":1.58},{"energy":1100.0,"cross_section":0.1474,"asymmetry_parameter":1.594},{"energy":1150.0,"cross_section":0.1385,"asymmetry_parameter":1.606},{"energy":1200.0,"cross_section":0.1303,"asymmetry_parameter":1.617},{"energy":1250.0,"cross_section":0.1227,"asymmetry_parameter":1.626},{"energy":1253.6,"cross_section":0.1222,"asymmetry_parameter":1.626},{"energy":1300.0,"cross_section":0.1158,"asymmetry_parameter":1.634},{"energy":1350.0,"cross_section":0.1094,"asymmetry_parameter":1.641},{"energy":1400.0,"cross_section":0.1034,"asymmetry_parameter":1.647},{"energy":1450.0,"cross_section":0.09794,"asymmetry_parameter":1.652},{"energy":1486.6,"cross_section":0.09418,"asymmetry_parameter":1.656},{"energy":1500.0,"cross_section":0.09285,"asymmetry_parameter":1.657}]